_sbrl.so
pysbrl/train.py
pysbrl/rule_list.py
pysbrl/__init__.py
pysbrl/utils.py
pysbrl/sbrl.py
.libs_sbrl/libgslcblas-51d797dd.so.0.0.0
.libs_sbrl/libgsl-55671716.so.0.14.0
pysbrl-0.4.2.dist-info/WHEEL
pysbrl-0.4.2.dist-info/RECORD
pysbrl-0.4.2.dist-info/dependency_links.txt
pysbrl-0.4.2.dist-info/METADATA
pysbrl-0.4.2.dist-info/top_level.txt
