Metadata-Version: 2.1
Name: pysbrl
Version: 0.4.2
Summary: A python interface of Scalable Bayesian Rule List
Home-page: https://github.com/myaooo/pysbrl
Author: Yao, Ming
Author-email: UNKNOWN
License: UNKNOWN
Platform: UNKNOWN
Requires-Dist: numpy (>=1.13fim)
